entity/__init__.py
entity/apps.py
entity/conf.py
entity/fields.py
entity/pagination.py
entity/urls.py
entity/admin/__init__.py
entity/admin/organization.py
entity/admin/person.py
entity/migrations/0001_initial.py
entity/migrations/0002_auto_20180117_2043.py
entity/migrations/0003_auto_20180608_1724.py
entity/migrations/0004_auto_20190104_1616.py
entity/migrations/__init__.py
entity/models/__init__.py
entity/models/image_tag.py
entity/models/organization.py
entity/models/organization_classification.py
entity/models/organization_image.py
entity/models/person.py
entity/models/person_image.py
entity/serializers/__init__.py
entity/serializers/image_tag.py
entity/serializers/organization.py
entity/serializers/organization_classification.py
entity/serializers/person.py
entity/utils/__init__.py
entity/utils/aws.py
entity/utils/importers.py
entity/viewsets/__init__.py
entity/viewsets/base.py
entity/viewsets/image_tag.py
entity/viewsets/organization.py
entity/viewsets/organization_classification.py
entity/viewsets/person.py
politico_civic_entity-0.3.1.dist-info/LICENSE
politico_civic_entity-0.3.1.dist-info/METADATA
politico_civic_entity-0.3.1.dist-info/WHEEL
politico_civic_entity-0.3.1.dist-info/top_level.txt
politico_civic_entity-0.3.1.dist-info/RECORD
