Metadata-Version: 2.1
Name: politico-civic-entity
Version: 0.3.1
Summary: UNKNOWN
Home-page: https://github.com/The-Politico/politico-civic-entity
Author: POLITICO interactive news
Author-email: interactives@politico.com
License: MIT
Platform: UNKNOWN
Classifier: Development Status :: 3 - Alpha
Classifier: Framework :: Django
Classifier: Framework :: Django :: 2.0
Classifier: Intended Audience :: Developers
Classifier: Intended Audience :: Information Technology
Classifier: License :: OSI Approved :: MIT License
Classifier: Operating System :: OS Independent
Classifier: Programming Language :: Python :: 3
Classifier: Programming Language :: Python :: 3.5
Classifier: Programming Language :: Python :: 3.6
Classifier: Topic :: Internet :: WWW/HTTP
Requires-Dist: pycountry
Requires-Dist: us
Requires-Dist: django
Requires-Dist: django-uuslug
Requires-Dist: djangorestframework
Requires-Dist: django-storages
Requires-Dist: boto3
Requires-Dist: Pillow
Requires-Dist: psycopg2
Provides-Extra: test
Requires-Dist: pytest ; extra == 'test'
